[
  {
    "id": 1,
    "title": "Queue and Deque",
    "category": "Data Structures and Algorithms",
    "image": "/projects/queue.png",
    "description": "A data structure project implementing queue and deque functionalities.",
    "technologies": ["Python"],
  "link": "/works/queue"
  },
  {
    "id": 2,
    "title": "Binary Tree",
    "category": "Data Structures and Algorithms",
    "image": "/projects/binary.png",
    "description": "A data structure project implementing binary tree functionalities.",
    "technologies": ["Python"],
    "link": "/works/binarytree"
  },
  {
    "id": 3,
    "title": "Binary Search Tree",
    "category": "Data Structures and Algorithms",
    "image": "/projects/bst.png",
    "description": "A data structure project implementing binary search tree functionalities.",
    "technologies": ["Python"],
    "link": "/works/binarysearchtree"
  },
  {
    "id": 4,
    "title": "Breadth-First Search",
    "category": "Data Structures and Algorithms",
    "image": "/projects/breadthfirst.png",
    "description": "A data structure project implementing breadth-first search algorithm using an MRT/LRT network graph simulator.",
    "technologies": ["Python"],
    "link": "/works/breadthfirstsearch"
  },
  {
    "id": 5,
    "title": "Sorting Algorithms",
    "category": "Data Structures and Algorithms",
    "image": "/projects/sorting.png",
    "description": "A data structure project implementing various sorting algorithms.",
    "technologies": ["Python"],
    "link": "/works/sortingalgorithms"
  },
  {
    "id": 6,
    "title": "Coming Soon",
    "category": "Data Structures and Algorithms",
    "image": "/projects/coming-soon.png",
    "description": "This project is coming soon.",
    "technologies": ["Python"],
    "link": ""
  }
]
